LICENSE
MANIFEST.in
README.rst
setup.py
django_kk.egg-info/PKG-INFO
django_kk.egg-info/SOURCES.txt
django_kk.egg-info/dependency_links.txt
django_kk.egg-info/requires.txt
django_kk.egg-info/top_level.txt
kk/__init__.py
kk/admin.py
kk/apps.py
kk/managers.py
kk/models.py
kk/utils.py
kk/views.py
kk/api/__init__.py
kk/api/views.py
kk/article/__init__.py
kk/article/admin.py
kk/article/models.py
kk/base/__init__.py
kk/base/admin.py
kk/base/models.py
kk/gallery/__init__.py
kk/gallery/admin.py
kk/gallery/models.py
kk/templates/kk/widgets/image.html
kk/text/__init__.py
kk/text/admin.py
kk/text/models.py
kk/uploads/__init__.py
kk/uploads/admin.py
kk/uploads/models.py