Metadata-Version: 1.1
Name: django-kk
Version: 0.1.4
Summary: Kenzo Kit for Django.
Home-page: https://icw82.ru/
Author: icw82
Author-email: icw82@yandex.ru
License: MIT
Keywords: REST API JSON
Platform: UNKNOWN
Classifier: Development Status :: 3 - Alpha
Classifier: Environment :: Web Environment
Classifier: Framework :: Django
Classifier: Framework :: Django :: 2.0
Classifier: Intended Audience :: Developers
Classifier: License :: OSI Approved :: MIT License
Classifier: Natural Language :: Russian
Classifier: Operating System :: OS Independent
Classifier: Programming Language :: Python
Classifier: Programming Language :: Python :: 3 :: Only
Classifier: Programming Language :: Python :: 3.5
Classifier: Programming Language :: Python :: 3.6
Classifier: Topic :: Software Development :: Libraries
